fire_chat/__init__.py
fire_chat/chat.py
fire_chat/config.py
fire_chat/constants.py
fire_chat/main.py
fire_chat/message.py
fire_chat/tools/__init__.py
fire_chat/tools/budget.py
fire_chat/tools/history.py
fire_chat/tools/model.py
fire_chat/tools/provider.py
fire_chat/ui/__init__.py
fire_chat/ui/console.py
fire_chat/ui/key_binding.py
fire_chat-0.0.6.dist-info/METADATA
fire_chat-0.0.6.dist-info/WHEEL
fire_chat-0.0.6.dist-info/entry_points.txt
fire_chat-0.0.6.dist-info/licenses/LICENSE
fire_chat-0.0.6.dist-info/RECORD
