Metadata-Version: 2.3
Name: fire-chat
Version: 0.0.6
Summary: A CLI tool to chat with LLM models including GPT and Claude.
Project-URL: Homepage, https://github.com/TiansuYu/fire-chat
Project-URL: Issues, https://github.com/TiansuYu/fire-chat/issues
Project-URL: Repository, https://github.com/TiansuYu/fire-chat
Author-email: Tiansu Yu <tiansu.yu@icloud.com>, Marco Lardera <larderamarco@hotmail.com>, Tadeas Fort <business@tadeasfort.com>
Maintainer-email: Tiansu Yu <tiansu.yu@icloud.com>, Tadeas Fort <business@tadeasfort.com>
License-Expression: Apache-2.0
License-File: LICENSE
Keywords: LLM,anthropic,chatGPT,claude,cli,openai
Classifier: Development Status :: 3 - Alpha
Classifier: License :: OSI Approved :: Apache Software License
Classifier: Natural Language :: English
Classifier: Operating System :: OS Independent
Classifier: Programming Language :: Python :: 3.10
Classifier: Programming Language :: Python :: 3.11
Classifier: Programming Language :: Python :: 3.12
Classifier: Programming Language :: Python :: 3.13
Requires-Python: >=3.10
Requires-Dist: fsspec>=2024.6.1
Requires-Dist: importlib-metadata>=8.2.0
Requires-Dist: litellm>=1.44.5
Requires-Dist: prompt-toolkit>=3.0.47
Requires-Dist: pydantic-collections>=0.6.0
Requires-Dist: pydantic>=2.8.2
Requires-Dist: pyyaml>=6.0.2
Requires-Dist: rich>=13.7.1
Requires-Dist: typer-config>=1.4.0
Requires-Dist: typer>=0.12.5
Requires-Dist: typing-extensions>=4.12.2
Requires-Dist: xdg-base-dirs>=6.0.1
